MANIFEST.in
setup.py
Kickstand.egg-info/PKG-INFO
Kickstand.egg-info/SOURCES.txt
Kickstand.egg-info/dependency_links.txt
Kickstand.egg-info/top_level.txt
inspections/memory/inspect
inspections/memory/structure.yaml
inspections/os/inspect
inspections/os/structure.yaml
kickstand/Communicator.py
kickstand/Configuration.py
kickstand/Constants.py
kickstand/Inspection.py
kickstand/Inspector.py
kickstand/ShellCommand.py
kickstand/__init__.py
kickstand/inventory/Category.py
kickstand/inventory/Group.py
kickstand/inventory/Machine.py
kickstand/inventory/Status.py
kickstand/inventory/__init__.py
scripts/kickstand