Metadata-Version: 1.0
Name: Kickstand
Version: 1.0.5.post8
Summary: Machine inventory management system client API
Home-page: http://www.rcac.purdue.edu
Author: Seth Cook
Author-email: sethcook@purdue.edu
License: Copyright (c) 2015, Purdue University
Platform: UNKNOWN
Classifier: Programming Language :: Python :: 2.6
Classifier: Programming Language :: Python :: 2.7
Classifier: Operating System :: Unix
Classifier: Development Status :: 4 - Beta
